gbpcli-3.3.0.dist-info/METADATA
gbpcli-3.3.0.dist-info/WHEEL
gbpcli-3.3.0.dist-info/entry_points.txt
gbpcli-3.3.0.dist-info/licenses/LICENSE
gbpcli/__init__.py
gbpcli/__main__.py
gbpcli/config.py
gbpcli/django_settings.py
gbpcli/gbp.py
gbpcli/graphql.py
gbpcli/py.typed
gbpcli/queries/build.graphql
gbpcli/queries/builds.graphql
gbpcli/queries/create_note.graphql
gbpcli/queries/diff.graphql
gbpcli/queries/keep_build.graphql
gbpcli/queries/latest.graphql
gbpcli/queries/logs.graphql
gbpcli/queries/machine_names.graphql
gbpcli/queries/machines.graphql
gbpcli/queries/packages.graphql
gbpcli/queries/publish.graphql
gbpcli/queries/pull.graphql
gbpcli/queries/release_build.graphql
gbpcli/queries/resolve_tag.graphql
gbpcli/queries/schedule_build.graphql
gbpcli/queries/search.graphql
gbpcli/queries/tag_build.graphql
gbpcli/queries/untag_build.graphql
gbpcli/render.py
gbpcli/settings.py
gbpcli/subcommands/__init__.py
gbpcli/subcommands/build.py
gbpcli/subcommands/completers.py
gbpcli/subcommands/diff.py
gbpcli/subcommands/inspect.py
gbpcli/subcommands/keep.py
gbpcli/subcommands/latest.py
gbpcli/subcommands/list.py
gbpcli/subcommands/logs.py
gbpcli/subcommands/machines.py
gbpcli/subcommands/notes.py
gbpcli/subcommands/packages.py
gbpcli/subcommands/publish.py
gbpcli/subcommands/pull.py
gbpcli/subcommands/status.py
gbpcli/subcommands/tag.py
gbpcli/theme.py
gbpcli/types.py
gbpcli/utils.py
gbpcli-3.3.0.dist-info/RECORD
