Metadata-Version: 2.1
Name: gbpcli
Version: 3.3.0
Summary: Gentoo Build Publisher Command-Line Interface
Author-Email: Albert Hopkins <marduk@letterboxes.org>
License: GPL3+
Classifier: Environment :: Console
Classifier: License :: OSI Approved :: GNU General Public License v3 or later (GPLv3+)
Classifier: Operating System :: POSIX :: Linux
Classifier: Topic :: System :: Software Distribution
Classifier: Programming Language :: Python :: 3
Project-URL: homepage, https://github.com/enku/gbpcli
Project-URL: repository, https://github.com/enku/gbpcli
Requires-Python: >=3.12
Requires-Dist: argcomplete>=3.2.1
Requires-Dist: requests
Requires-Dist: rich>=12.5.1
Requires-Dist: yarl
Requires-Dist: platformdirs>=4.2.0
Requires-Dist: distutils-strtobool>=0.1.0
Requires-Dist: python-dotenv>=1.0.1
